odoo/addons/coupon_portal/README.rst
odoo/addons/coupon_portal/__init__.py
odoo/addons/coupon_portal/__manifest__.py
odoo/addons/coupon_portal/controllers/__init__.py
odoo/addons/coupon_portal/controllers/portal.py
odoo/addons/coupon_portal/i18n/coupon_portal.pot
odoo/addons/coupon_portal/i18n/es.po
odoo/addons/coupon_portal/readme/CONFIGURE.rst
odoo/addons/coupon_portal/readme/CONTRIBUTORS.rst
odoo/addons/coupon_portal/readme/DESCRIPTION.rst
odoo/addons/coupon_portal/readme/USAGE.rst
odoo/addons/coupon_portal/static/description/icon.svg
odoo/addons/coupon_portal/static/description/index.html
odoo/addons/coupon_portal/static/src/js/tour_coupon_portal.js
odoo/addons/coupon_portal/templates/coupon_portal_templates.xml
odoo/addons/coupon_portal/tests/__init__.py
odoo/addons/coupon_portal/tests/test_coupon_portal.py
odoo_addon_coupon_portal-15.0.1.0.0.4.dist-info/METADATA
odoo_addon_coupon_portal-15.0.1.0.0.4.dist-info/WHEEL
odoo_addon_coupon_portal-15.0.1.0.0.4.dist-info/top_level.txt
odoo_addon_coupon_portal-15.0.1.0.0.4.dist-info/RECORD
